sap_bdc_mcp/__init__.py
sap_bdc_mcp/__main__.py
sap_bdc_mcp/config.py
sap_bdc_mcp/plugin_loader.py
sap_bdc_mcp/policy.py
sap_bdc_mcp/redaction.py
sap_bdc_mcp/server.py
sap_bdc_mcp/connectors/__init__.py
sap_bdc_mcp/connectors/csn_client.py
sap_bdc_mcp/connectors/ord_client.py
sap_bdc_mcp/connectors/ord_schema.py
sap_bdc_mcp/models/__init__.py
sap_bdc_mcp/models/share_plan.py
sap_bdc_mcp/schemas/__init__.py
sap_bdc_mcp/schemas/ord/Configuration.schema.json
sap_bdc_mcp/schemas/ord/Document.schema.json
sap_bdc_mcp/schemas/ord/__init__.py
sap_bdc_mcp/tools/__init__.py
sap_bdc_mcp/tools/core.py
sap_bdc_mcp/tools/csn_tools.py
sap_bdc_mcp/tools/ord_tools.py
sap_bdc_mcp/tools/registry.py
sap_bdc_mcp/tools/share_tools.py
sap_bdc_mcp-0.1.0.dist-info/licenses/LICENSE
sap_bdc_mcp-0.1.0.dist-info/METADATA
sap_bdc_mcp-0.1.0.dist-info/WHEEL
sap_bdc_mcp-0.1.0.dist-info/entry_points.txt
sap_bdc_mcp-0.1.0.dist-info/top_level.txt
sap_bdc_mcp-0.1.0.dist-info/RECORD
