Metadata-Version: 2.4
Name: sap-bdc-mcp
Version: 0.1.0
Summary: Model Context Protocol (MCP) server for SAP Business Data Cloud (BDC): contract-first, safe-by-default tooling for AI agents.
Author: Rahul Sethi
License: MIT
Project-URL: Homepage, https://github.com/rahulsethi/SAPBDCMCP
Project-URL: Repository, https://github.com/rahulsethi/SAPBDCMCP
Project-URL: Issues, https://github.com/rahulsethi/SAPBDCMCP/issues
Keywords: mcp,sap,business-data-cloud,bdc,ord,csn,agentic,ai-tools
Classifier: Development Status :: 3 - Alpha
Classifier: Intended Audience :: Developers
Classifier: License :: OSI Approved :: MIT License
Classifier: Programming Language :: Python :: 3
Classifier: Programming Language :: Python :: 3 :: Only
Classifier: Programming Language :: Python :: 3.11
Classifier: Programming Language :: Python :: 3.12
Classifier: Programming Language :: Python :: 3.13
Classifier: Topic :: Software Development :: Libraries
Classifier: Topic :: Scientific/Engineering :: Information Analysis
Requires-Python: >=3.11
License-File: LICENSE
Requires-Dist: mcp[cli]>=1.25.0
Requires-Dist: pydantic>=2.7.0
Requires-Dist: httpx>=0.27.0
Requires-Dist: python-dotenv>=1.0.1
Requires-Dist: jsonschema>=4.20.0
Provides-Extra: dev
Requires-Dist: pytest>=8.0.0; extra == "dev"
Requires-Dist: pytest-cov>=5.0.0; extra == "dev"
Requires-Dist: ruff>=0.6.0; extra == "dev"
Requires-Dist: mypy>=1.10.0; extra == "dev"
Requires-Dist: pre-commit>=3.7.0; extra == "dev"
Requires-Dist: build>=1.2.2; extra == "dev"
Requires-Dist: twine>=5.1.1; extra == "dev"
Dynamic: license-file
